fundingextractor/__init__.py
fundingextractor/main.py
fundingextractor/prompts.py
fundingextractor-2025.12.21141421.dist-info/METADATA
fundingextractor-2025.12.21141421.dist-info/WHEEL
fundingextractor-2025.12.21141421.dist-info/top_level.txt
fundingextractor-2025.12.21141421.dist-info/RECORD
