Metadata-Version: 2.4
Name: fundingextractor
Version: 2025.12.21141421
Summary: A new package that processes news headlines and extracts structured information about company funding events, such as startup names, valuation amounts, and funding rounds, using pattern matching to en
Author-email: fundingextractor <hi@eugene.plus>
License: MIT
Project-URL: Homepage, https://github.com/chigwell/fundingextractor
Requires-Python: >=3.9
Requires-Dist: langchain-llm7>=0.0.0
Requires-Dist: llmatch-messages>=0.0.0
Requires-Dist: langchain-core>=0.3.0
